LICENSE
MANIFEST.in
README.md
setup.py
virtme/__init__.py
virtme/architectures.py
virtme/cpiowriter.py
virtme/guest_tools.py
virtme/mkinitramfs.py
virtme/modfinder.py
virtme/qemu_helpers.py
virtme/virtmods.py
virtme.egg-info/PKG-INFO
virtme.egg-info/SOURCES.txt
virtme.egg-info/dependency_links.txt
virtme.egg-info/entry_points.txt
virtme.egg-info/top_level.txt
virtme/commands/__init__.py
virtme/commands/configkernel.py
virtme/commands/run.py
virtme/guest/virtme-init
virtme/guest/virtme-loadmods
virtme/guest/virtme-udhcpc-script