Metadata-Version: 1.1
Name: virtme
Version: 0.0.1
Summary: Virtualize the running distro or a simple rootfs
Home-page: https://git.kernel.org/cgit/utils/kernel/virtme/virtme.git
Author: Andy Lutomirski
Author-email: luto@amacapital.net
License: GPLv2
Download-URL: https://www.kernel.org/pub/linux/utils/kernel/virtme/releases/virtme-0.0.1.tar.xz
Platform: UNKNOWN
Classifier: Environment :: Console
Classifier: Intended Audience :: Developers
Classifier: Intended Audience :: System Administrators
Classifier: License :: OSI Approved :: GNU General Public License v2 (GPLv2)
Classifier: Operating System :: POSIX :: Linux
